Verilog/src/PseudoPLL.v
//Modulo que recibe como entrada un clock de 1Mhz
//y devuelve un clock de una frecuencia definida por freq_param;
//la f_clk del ouput esta definida como:
//  f_clk= (MIN_CLK_STEP*freq_param)+F_CLK_MIN


module PseudoPll(
  clk_in,
  freq_param,
  clk_out
);
//Parametros
parameter F_CLK_MIN = 6000;
parameter F_CLK_MAX = 100000;
parameter MIN_CLK_STEP =(F_CLK_MAX-F_CLK_MIN)/256;

input wire clk_in;
input wire [7:0] freq_param;
output reg clk_out;
reg [15:0] counter;
reg a;
reg [31:0] desired_clk;
reg [31:0] edges_per_on_cycle;
initial begin
  counter=0;
  clk_out=0;
end


always @(posedge clk_in) begin
  desired_clk <= (MIN_CLK_STEP*freq_param)+F_CLK_MIN;
  edges_per_on_cycle <= 1/(desired_clk*2*0.000001);
  if (counter < (edges_per_on_cycle-1)) begin //Aumenta el contador con cada flanco ascendente
    counter <= counter +1;
  end
  else begin
    counter <=0;
    clk_out <= ~clk_out;
  end

end

endmodule // PseudoPll

Quartus/Verilog/VariableClock/src/clock.v
`timescale 1ps / 1ps
module clock_gen(clk);

parameter PERIOD = 20000;

output reg clk;
	 
always
	begin: CLOCK_DRIVER
		clk <= 1'b0;
		#(PERIOD/2);
		clk <= 1'b1;
		#(PERIOD/2);
	end
endmodule

Verilog/src/PseudoPLL_tb.v
//Testbench que se encarga de probar el modulo
//PseudoPll

`timescale 1ms / 100us

module PseudoPll_tb;
 wire clk_in;
 wire clk_out;
 reg[7:0] freq_param;
 clock_gen clk_inst(clk_in);
 PseudoPll inst(clk_in,freq_param ,clk_out);

 initial begin
   freq_param= 100;
   #30;
   $finish;
 end

 reg dummy;
    reg[8*64:0] dumpfile_path = "output.vcd";

    initial begin
        dummy = $value$plusargs("VCD_PATH=%s", dumpfile_path);
        $dumpfile(dumpfile_path);
        $dumpvars(0,PseudoPll_tb);
    end

endmodule // PseudoPll_tb

Verilog/bin/output.vcd
$date
	Mon May 20 13:02:01 2019
$end
$version
	Icarus Verilog
$end
$timescale
	1ps
$end
$scope module PseudoPll_tb $end
$var wire 1 ! clk_out $end
$var wire 1 " clk_in $end
$var reg 1 # dummy $end
$var reg 513 $ dumpfile_path [512:0] $end
$var reg 8 % freq_param [7:0] $end
$scope module clk_inst $end
$var reg 1 " clk $end
$scope begin CLOCK_DRIVER $end
$upscope $end
$upscope $end
$scope module inst $end
$var wire 1 " clk_in $end
$var wire 8 & freq_param [7:0] $end
$var reg 1 ! clk_out $end
$var reg 16 ' counter [15:0] $end
$var reg 32 ( desired_clk [31:0] $end
$var reg 32 ) edges_per_on_cycle [31:0] $end
$upscope $end
$upscope $end
$enddefinitions $end
#0
$dumpvars
bx )
bx (
b0 '
b1100100 &
b1100100 %
b110001001101001011011100010111101101111011101010111010001110000011101010111010000101110011101100110001101100100 $
1#
0"
0!
$end
#500000
1!
b1010011011001100 (
1"
#1000000
0"
#1500000
0!
b1100 )
1"
#2000000
0"
#2500000
b1 '
1"
#3000000
0"
#3500000
b10 '
1"
#4000000
0"
#4500000
b11 '
1"
#5000000
0"
#5500000
b100 '
1"
#6000000
0"
#6500000
b101 '
1"
#7000000
0"
#7500000
b110 '
1"
#8000000
0"
#8500000
b111 '
1"
#9000000
0"
#9500000
b1000 '
1"
#10000000
0"
#10500000
b1001 '
1"
#11000000
0"
#11500000
b1010 '
1"
#12000000
0"
#12500000
b1011 '
1"
#13000000
0"
#13500000
1!
b0 '
1"
#14000000
0"
#14500000
b1 '
1"
#15000000
0"
#15500000
b10 '
1"
#16000000
0"
#16500000
b11 '
1"
#17000000
0"
#17500000
b100 '
1"
#18000000
0"
#18500000
b101 '
1"
#19000000
0"
#19500000
b110 '
1"
#20000000
0"
#20500000
b111 '
1"
#21000000
0"
#21500000
b1000 '
1"
#22000000
0"
#22500000
b1001 '
1"
#23000000
0"
#23500000
b1010 '
1"
#24000000
0"
#24500000
b1011 '
1"
#25000000
0"
#25500000
0!
b0 '
1"
#26000000
0"
#26500000
b1 '
1"
#27000000
0"
#27500000
b10 '
1"
#28000000
0"
#28500000
b11 '
1"
#29000000
0"
#29500000
b100 '
1"
#30000000
0"
#30500000
b101 '
1"
#31000000
0"
#31500000
b110 '
1"
#32000000
0"
#32500000
b111 '
1"
#33000000
0"
#33500000
b1000 '
1"
#34000000
0"
#34500000
b1001 '
1"
#35000000
0"
#35500000
b1010 '
1"
#36000000
0"
#36500000
b1011 '
1"
#37000000
0"
#37500000
1!
b0 '
1"
#38000000
0"
#38500000
b1 '
1"
#39000000
0"
#39500000
b10 '
1"
#40000000
0"
#40500000
b11 '
1"
#41000000
0"
#41500000
b100 '
1"
#42000000
0"
#42500000
b101 '
1"
#43000000
0"
#43500000
b110 '
1"
#44000000
0"
#44500000
b111 '
1"
#45000000
0"
#45500000
b1000 '
1"
#46000000
0"
#46500000
b1001 '
1"
#47000000
0"
#47500000
b1010 '
1"
#48000000
0"
#48500000
b1011 '
1"
#49000000
0"
#49500000
0!
b0 '
1"
#50000000
0"
#50500000
b1 '
1"
#51000000
0"
#51500000
b10 '
1"
#52000000
0"
#52500000
b11 '
1"
#53000000
0"
#53500000
b100 '
1"
#54000000
0"
#54500000
b101 '
1"
#55000000
0"
#55500000
b110 '
1"
#56000000
0"
#56500000
b111 '
1"
#57000000
0"
#57500000
b1000 '
1"
#58000000
0"
#58500000
b1001 '
1"
#59000000
0"
#59500000
b1010 '
1"
#60000000
0"
#60500000
b1011 '
1"
#61000000
0"
#61500000
1!
b0 '
1"
#62000000
0"
#62500000
b1 '
1"
#63000000
0"
#63500000
b10 '
1"
#64000000
0"
#64500000
b11 '
1"
#65000000
0"
#65500000
b100 '
1"
#66000000
0"
#66500000
b101 '
1"
#67000000
0"
#67500000
b110 '
1"
#68000000
0"
#68500000
b111 '
1"
#69000000
0"
#69500000
b1000 '
1"
#70000000
0"
#70500000
b1001 '
1"
#71000000
0"
#71500000
b1010 '
1"
#72000000
0"
#72500000
b1011 '
1"
#73000000
0"
#73500000
0!
b0 '
1"
#74000000
0"
#74500000
b1 '
1"
#75000000
0"
#75500000
b10 '
1"
#76000000
0"
#76500000
b11 '
1"
#77000000
0"
#77500000
b100 '
1"
#78000000
0"
#78500000
b101 '
1"
#79000000
0"
#79500000
b110 '
1"
#80000000
0"
#80500000
b111 '
1"
#81000000
0"
#81500000
b1000 '
1"
#82000000
0"
#82500000
b1001 '
1"
#83000000
0"
#83500000
b1010 '
1"
#84000000
0"
#84500000
b1011 '
1"
#85000000
0"
#85500000
1!
b0 '
1"
#86000000
0"
#86500000
b1 '
1"
#87000000
0"
#87500000
b10 '
1"
#88000000
0"
#88500000
b11 '
1"
#89000000
0"
#89500000
b100 '
1"
#90000000
0"
#90500000
b101 '
1"
#91000000
0"
#91500000
b110 '
1"
#92000000
0"
#92500000
b111 '
1"
#93000000
0"
#93500000
b1000 '
1"
#94000000
0"
#94500000
b1001 '
1"
#95000000
0"
#95500000
b1010 '
1"
#96000000
0"
#96500000
b1011 '
1"
#97000000
0"
#97500000
0!
b0 '
1"
#98000000
0"
#98500000
b1 '
1"
#99000000
0"
#99500000
b10 '
1"
#100000000
0"
#100500000
b11 '
1"
#101000000
0"
#101500000
b100 '
1"
#102000000
0"
#102500000
b101 '
1"
#103000000
0"
#103500000
b110 '
1"
#104000000
0"
#104500000
b111 '
1"
#105000000
0"
#105500000
b1000 '
1"
#106000000
0"
#106500000
b1001 '
1"
#107000000
0"
#107500000
b1010 '
1"
#108000000
0"
#108500000
b1011 '
1"
#109000000
0"
#109500000
1!
b0 '
1"
#110000000
0"
#110500000
b1 '
1"
#111000000
0"
#111500000
b10 '
1"
#112000000
0"
#112500000
b11 '
1"
#113000000
0"
#113500000
b100 '
1"
#114000000
0"
#114500000
b101 '
1"
#115000000
0"
#115500000
b110 '
1"
#116000000
0"
#116500000
b111 '
1"
#117000000
0"
#117500000
b1000 '
1"
#118000000
0"
#118500000
b1001 '
1"
#119000000
0"
#119500000
b1010 '
1"
#120000000
0"
#120500000
b1011 '
1"
#121000000
0"
#121500000
0!
b0 '
1"
#122000000
0"
#122500000
b1 '
1"
#123000000
0"
#123500000
b10 '
1"
#124000000
0"
#124500000
b11 '
1"
#125000000
0"
#125500000
b100 '
1"
#126000000
0"
#126500000
b101 '
1"
#127000000
0"
#127500000
b110 '
1"
#128000000
0"
#128500000
b111 '
1"
#129000000
0"
#129500000
b1000 '
1"
#130000000
0"
#130500000
b1001 '
1"
#131000000
0"
#131500000
b1010 '
1"
#132000000
0"
#132500000
b1011 '
1"
#133000000
0"
#133500000
1!
b0 '
1"
#134000000
0"
#134500000
b1 '
1"
#135000000
0"
#135500000
b10 '
1"
#136000000
0"
#136500000
b11 '
1"
#137000000
0"
#137500000
b100 '
1"
#138000000
0"
#138500000
b101 '
1"
#139000000
0"
#139500000
b110 '
1"
#140000000
0"
#140500000
b111 '
1"
#141000000
0"
#141500000
b1000 '
1"
#142000000
0"
#142500000
b1001 '
1"
#143000000
0"
#143500000
b1010 '
1"
#144000000
0"
#144500000
b1011 '
1"
#145000000
0"
#145500000
0!
b0 '
1"
#146000000
0"
#146500000
b1 '
1"
#147000000
0"
#147500000
b10 '
1"
#148000000
0"
#148500000
b11 '
1"
#149000000
0"
#149500000
b100 '
1"
#150000000
0"
#150500000
b101 '
1"
#151000000
0"
#151500000
b110 '
1"
#152000000
0"
#152500000
b111 '
1"
#153000000
0"
#153500000
b1000 '
1"
#154000000
0"
#154500000
b1001 '
1"
#155000000
0"
#155500000
b1010 '
1"
#156000000
0"
#156500000
b1011 '
1"
#157000000
0"
#157500000
1!
b0 '
1"
#158000000
0"
#158500000
b1 '
1"
#159000000
0"
#159500000
b10 '
1"
#160000000
0"
#160500000
b11 '
1"
#161000000
0"
#161500000
b100 '
1"
#162000000
0"
#162500000
b101 '
1"
#163000000
0"
#163500000
b110 '
1"
#164000000
0"
#164500000
b111 '
1"
#165000000
0"
#165500000
b1000 '
1"
#166000000
0"
#166500000
b1001 '
1"
#167000000
0"
#167500000
b1010 '
1"
#168000000
0"
#168500000
b1011 '
1"
#169000000
0"
#169500000
0!
b0 '
1"
#170000000
0"
#170500000
b1 '
1"
#171000000
0"
#171500000
b10 '
1"
#172000000
0"
#172500000
b11 '
1"
#173000000
0"
#173500000
b100 '
1"
#174000000
0"
#174500000
b101 '
1"
#175000000
0"
#175500000
b110 '
1"
#176000000
0"
#176500000
b111 '
1"
#177000000
0"
#177500000
b1000 '
1"
#178000000
0"
#178500000
b1001 '
1"
#179000000
0"
#179500000
b1010 '
1"
#180000000
0"
#180500000
b1011 '
1"
#181000000
0"
#181500000
1!
b0 '
1"
#182000000
0"
#182500000
b1 '
1"
#183000000
0"
#183500000
b10 '
1"
#184000000
0"
#184500000
b11 '
1"
#185000000
0"
#185500000
b100 '
1"
#186000000
0"
#186500000
b101 '
1"
#187000000
0"
#187500000
b110 '
1"
#188000000
0"
#188500000
b111 '
1"
#189000000
0"
#189500000
b1000 '
1"
#190000000
0"
#190500000
b1001 '
1"
#191000000
0"
#191500000
b1010 '
1"
#192000000
0"
#192500000
b1011 '
1"
#193000000
0"
#193500000
0!
b0 '
1"
#194000000
0"
#194500000
b1 '
1"
#195000000
0"
#195500000
b10 '
1"
#196000000
0"
#196500000
b11 '
1"
#197000000
0"
#197500000
b100 '
1"
#198000000
0"
#198500000
b101 '
1"
#199000000
0"
#199500000
b110 '
1"
#200000000
0"
#200500000
b111 '
1"
#201000000
0"
#201500000
b1000 '
1"
#202000000
0"
#202500000
b1001 '
1"
#203000000
0"
#203500000
b1010 '
1"
#204000000
0"
#204500000
b1011 '
1"
#205000000
0"
#205500000
1!
b0 '
1"
#206000000
0"
#206500000
b1 '
1"
#207000000
0"
#207500000
b10 '
1"
#208000000
0"
#208500000
b11 '
1"
#209000000
0"
#209500000
b100 '
1"
#210000000
0"
#210500000
b101 '
1"
#211000000
0"
#211500000
b110 '
1"
#212000000
0"
#212500000
b111 '
1"
#213000000
0"
#213500000
b1000 '
1"
#214000000
0"
#214500000
b1001 '
1"
#215000000
0"
#215500000
b1010 '
1"
#216000000
0"
#216500000
b1011 '
1"
#217000000
0"
#217500000
0!
b0 '
1"
#218000000
0"
#218500000
b1 '
1"
#219000000
0"
#219500000
b10 '
1"
#220000000
0"
#220500000
b11 '
1"
#221000000
0"
#221500000
b100 '
1"
#222000000
0"
#222500000
b101 '
1"
#223000000
0"
#223500000
b110 '
1"
#224000000
0"
#224500000
b111 '
1"
#225000000
0"
#225500000
b1000 '
1"
#226000000
0"
#226500000
b1001 '
1"
#227000000
0"
#227500000
b1010 '
1"
#228000000
0"
#228500000
b1011 '
1"
#229000000
0"
#229500000
1!
b0 '
1"
#230000000
0"
#230500000
b1 '
1"
#231000000
0"
#231500000
b10 '
1"
#232000000
0"
#232500000
b11 '
1"
#233000000
0"
#233500000
b100 '
1"
#234000000
0"
#234500000
b101 '
1"
#235000000
0"
#235500000
b110 '
1"
#236000000
0"
#236500000
b111 '
1"
#237000000
0"
#237500000
b1000 '
1"
#238000000
0"
#238500000
b1001 '
1"
#239000000
0"
#239500000
b1010 '
1"
#240000000
0"
#240500000
b1011 '
1"
#241000000
0"
#241500000
0!
b0 '
1"
#242000000
0"
#242500000
b1 '
1"
#243000000
0"
#243500000
b10 '
1"
#244000000
0"
#244500000
b11 '
1"
#245000000
0"
#245500000
b100 '
1"
#246000000
0"
#246500000
b101 '
1"
#247000000
0"
#247500000
b110 '
1"
#248000000
0"
#248500000
b111 '
1"
#249000000
0"
#249500000
b1000 '
1"
#250000000
0"
#250500000
b1001 '
1"
#251000000
0"
#251500000
b1010 '
1"
#252000000
0"
#252500000
b1011 '
1"
#253000000
0"
#253500000
1!
b0 '
1"
#254000000
0"
#254500000
b1 '
1"
#255000000
0"
#255500000
b10 '
1"
#256000000
0"
#256500000
b11 '
1"
#257000000
0"
#257500000
b100 '
1"
#258000000
0"
#258500000
b101 '
1"
#259000000
0"
#259500000
b110 '
1"
#260000000
0"
#260500000
b111 '
1"
#261000000
0"
#261500000
b1000 '
1"
#262000000
0"
#262500000
b1001 '
1"
#263000000
0"
#263500000
b1010 '
1"
#264000000
0"
#264500000
b1011 '
1"
#265000000
0"
#265500000
0!
b0 '
1"
#266000000
0"
#266500000
b1 '
1"
#267000000
0"
#267500000
b10 '
1"
#268000000
0"
#268500000
b11 '
1"
#269000000
0"
#269500000
b100 '
1"
#270000000
0"
#270500000
b101 '
1"
#271000000
0"
#271500000
b110 '
1"
#272000000
0"
#272500000
b111 '
1"
#273000000
0"
#273500000
b1000 '
1"
#274000000
0"
#274500000
b1001 '
1"
#275000000
0"
#275500000
b1010 '
1"
#276000000
0"
#276500000
b1011 '
1"
#277000000
0"
#277500000
1!
b0 '
1"
#278000000
0"
#278500000
b1 '
1"
#279000000
0"
#279500000
b10 '
1"
#280000000
0"
#280500000
b11 '
1"
#281000000
0"
#281500000
b100 '
1"
#282000000
0"
#282500000
b101 '
1"
#283000000
0"
#283500000
b110 '
1"
#284000000
0"
#284500000
b111 '
1"
#285000000
0"
#285500000
b1000 '
1"
#286000000
0"
#286500000
b1001 '
1"
#287000000
0"
#287500000
b1010 '
1"
#288000000
0"
#288500000
b1011 '
1"
#289000000
0"
#289500000
0!
b0 '
1"
#290000000
0"
#290500000
b1 '
1"
#291000000
0"
#291500000
b10 '
1"
#292000000
0"
#292500000
b11 '
1"
#293000000
0"
#293500000
b100 '
1"
#294000000
0"
#294500000
b101 '
1"
#295000000
0"
#295500000
b110 '
1"
#296000000
0"
#296500000
b111 '
1"
#297000000
0"
#297500000
b1000 '
1"
#298000000
0"
#298500000
b1001 '
1"
#299000000
0"
#299500000
b1010 '
1"
#300000000
0"
#300500000
b1011 '
1"
#301000000
0"
#301500000
1!
b0 '
1"
#302000000
0"
#302500000
b1 '
1"
#303000000
0"
#303500000
b10 '
1"
#304000000
0"
#304500000
b11 '
1"
#305000000
0"
#305500000
b100 '
1"
#306000000
0"
#306500000
b101 '
1"
#307000000
0"
#307500000
b110 '
1"
#308000000
0"
#308500000
b111 '
1"
#309000000
0"
#309500000
b1000 '
1"
#310000000
0"
#310500000
b1001 '
1"
#311000000
0"
#311500000
b1010 '
1"
#312000000
0"
#312500000
b1011 '
1"
#313000000
0"
#313500000
0!
b0 '
1"
#314000000
0"
#314500000
b1 '
1"
#315000000
0"
#315500000
b10 '
1"
#316000000
0"
#316500000
b11 '
1"
#317000000
0"
#317500000
b100 '
1"
#318000000
0"
#318500000
b101 '
1"
#319000000
0"
#319500000
b110 '
1"
#320000000
0"
#320500000
b111 '
1"
#321000000
0"
#321500000
b1000 '
1"
#322000000
0"
#322500000
b1001 '
1"
#323000000
0"
#323500000
b1010 '
1"
#324000000
0"
#324500000
b1011 '
1"
#325000000
0"
#325500000
1!
b0 '
1"
#326000000
0"
#326500000
b1 '
1"
#327000000
0"
#327500000
b10 '
1"
#328000000
0"
#328500000
b11 '
1"
#329000000
0"
#329500000
b100 '
1"
#330000000
0"
#330500000
b101 '
1"
#331000000
0"
#331500000
b110 '
1"
#332000000
0"
#332500000
b111 '
1"
#333000000
0"
#333500000
b1000 '
1"
#334000000
0"
#334500000
b1001 '
1"
#335000000
0"
#335500000
b1010 '
1"
#336000000
0"
#336500000
b1011 '
1"
#337000000
0"
#337500000
0!
b0 '
1"
#338000000
0"
#338500000
b1 '
1"
#339000000
0"
#339500000
b10 '
1"
#340000000
0"
#340500000
b11 '
1"
#341000000
0"
#341500000
b100 '
1"
#342000000
0"
#342500000
b101 '
1"
#343000000
0"
#343500000
b110 '
1"
#344000000
0"
#344500000
b111 '
1"
#345000000
0"
#345500000
b1000 '
1"
#346000000
0"
#346500000
b1001 '
1"
#347000000
0"
#347500000
b1010 '
1"
#348000000
0"
#348500000
b1011 '
1"
#349000000
0"
#349500000
1!
b0 '
1"
#350000000
0"
#350500000
b1 '
1"
#351000000
0"
#351500000
b10 '
1"
#352000000
0"
#352500000
b11 '
1"
#353000000
0"
#353500000
b100 '
1"
#354000000
0"
#354500000
b101 '
1"
#355000000
0"
#355500000
b110 '
1"
#356000000
0"
#356500000
b111 '
1"
#357000000
0"
#357500000
b1000 '
1"
#358000000
0"
#358500000
b1001 '
1"
#359000000
0"
#359500000
b1010 '
1"
#360000000
0"
#360500000
b1011 '
1"
#361000000
0"
#361500000
0!
b0 '
1"
#362000000
0"
#362500000
b1 '
1"
#363000000
0"
#363500000
b10 '
1"
#364000000
0"
#364500000
b11 '
1"
#365000000
0"
#365500000
b100 '
1"
#366000000
0"
#366500000
b101 '
1"
#367000000
0"
#367500000
b110 '
1"
#368000000
0"
#368500000
b111 '
1"
#369000000
0"
#369500000
b1000 '
1"
#370000000
0"
#370500000
b1001 '
1"
#371000000
0"
#371500000
b1010 '
1"
#372000000
0"
#372500000
b1011 '
1"
#373000000
0"
#373500000
1!
b0 '
1"
#374000000
0"
#374500000
b1 '
1"
#375000000
0"
#375500000
b10 '
1"
#376000000
0"
#376500000
b11 '
1"
#377000000
0"
#377500000
b100 '
1"
#378000000
0"
#378500000
b101 '
1"
#379000000
0"
#379500000
b110 '
1"
#380000000
0"
#380500000
b111 '
1"
#381000000
0"
#381500000
b1000 '
1"
#382000000
0"
#382500000
b1001 '
1"
#383000000
0"
#383500000
b1010 '
1"
#384000000
0"
#384500000
b1011 '
1"
#385000000
0"
#385500000
0!
b0 '
1"
#386000000
0"
#386500000
b1 '
1"
#387000000
0"
#387500000
b10 '
1"
#388000000
0"
#388500000
b11 '
1"
#389000000
0"
#389500000
b100 '
1"
#390000000
0"
#390500000
b101 '
1"
#391000000
0"
#391500000
b110 '
1"
#392000000
0"
#392500000
b111 '
1"
#393000000
0"
#393500000
b1000 '
1"
#394000000
0"
#394500000
b1001 '
1"
#395000000
0"
#395500000
b1010 '
1"
#396000000
0"
#396500000
b1011 '
1"
#397000000
0"
#397500000
1!
b0 '
1"
#398000000
0"
#398500000
b1 '
1"
#399000000
0"
#399500000
b10 '
1"
#400000000
0"
#400500000
b11 '
1"
#401000000
0"
#401500000
b100 '
1"
#402000000
0"
#402500000
b101 '
1"
#403000000
0"
#403500000
b110 '
1"
#404000000
0"
#404500000
b111 '
1"
#405000000
0"
#405500000
b1000 '
1"
#406000000
0"
#406500000
b1001 '
1"
#407000000
0"
#407500000
b1010 '
1"
#408000000
0"
#408500000
b1011 '
1"
#409000000
0"
#409500000
0!
b0 '
1"
#410000000
0"
#410500000
b1 '
1"
#411000000
0"
#411500000
b10 '
1"
#412000000
0"
#412500000
b11 '
1"
#413000000
0"
#413500000
b100 '
1"
#414000000
0"
#414500000
b101 '
1"
#415000000
0"
#415500000
b110 '
1"
#416000000
0"
#416500000
b111 '
1"
#417000000
0"
#417500000
b1000 '
1"
#418000000
0"
#418500000
b1001 '
1"
#419000000
0"
#419500000
b1010 '
1"
#420000000
0"
#420500000
b1011 '
1"
#421000000
0"
#421500000
1!
b0 '
1"
#422000000
0"
#422500000
b1 '
1"
#423000000
0"
#423500000
b10 '
1"
#424000000
0"
#424500000
b11 '
1"
#425000000
0"
#425500000
b100 '
1"
#426000000
0"
#426500000
b101 '
1"
#427000000
0"
#427500000
b110 '
1"
#428000000
0"
#428500000
b111 '
1"
#429000000
0"
#429500000
b1000 '
1"
#430000000
0"
#430500000
b1001 '
1"
#431000000
0"
#431500000
b1010 '
1"
#432000000
0"
#432500000
b1011 '
1"
#433000000
0"
#433500000
0!
b0 '
1"
#434000000
0"
#434500000
b1 '
1"
#435000000
0"
#435500000
b10 '
1"
#436000000
0"
#436500000
b11 '
1"
#437000000
0"
#437500000
b100 '
1"
#438000000
0"
#438500000
b101 '
1"
#439000000
0"
#439500000
b110 '
1"
#440000000
0"
#440500000
b111 '
1"
#441000000
0"
#441500000
b1000 '
1"
#442000000
0"
#442500000
b1001 '
1"
#443000000
0"
#443500000
b1010 '
1"
#444000000
0"
#444500000
b1011 '
1"
#445000000
0"
#445500000
1!
b0 '
1"
#446000000
0"
#446500000
b1 '
1"
#447000000
0"
#447500000
b10 '
1"
#448000000
0"
#448500000
b11 '
1"
#449000000
0"
#449500000
b100 '
1"
#450000000
0"
#450500000
b101 '
1"
#451000000
0"
#451500000
b110 '
1"
#452000000
0"
#452500000
b111 '
1"
#453000000
0"
#453500000
b1000 '
1"
#454000000
0"
#454500000
b1001 '
1"
#455000000
0"
#455500000
b1010 '
1"
#456000000
0"
#456500000
b1011 '
1"
#457000000
0"
#457500000
0!
b0 '
1"
#458000000
0"
#458500000
b1 '
1"
#459000000
0"
#459500000
b10 '
1"
#460000000
0"
#460500000
b11 '
1"
#461000000
0"
#461500000
b100 '
1"
#462000000
0"
#462500000
b101 '
1"
#463000000
0"
#463500000
b110 '
1"
#464000000
0"
#464500000
b111 '
1"
#465000000
0"
#465500000
b1000 '
1"
#466000000
0"
#466500000
b1001 '
1"
#467000000
0"
#467500000
b1010 '
1"
#468000000
0"
#468500000
b1011 '
1"
#469000000
0"
#469500000
1!
b0 '
1"
#470000000
0"
#470500000
b1 '
1"
#471000000
0"
#471500000
b10 '
1"
#472000000
0"
#472500000
b11 '
1"
#473000000
0"
#473500000
b100 '
1"
#474000000
0"
#474500000
b101 '
1"
#475000000
0"
#475500000
b110 '
1"
#476000000
0"
#476500000
b111 '
1"
#477000000
0"
#477500000
b1000 '
1"
#478000000
0"
#478500000
b1001 '
1"
#479000000
0"
#479500000
b1010 '
1"
#480000000
0"
#480500000
b1011 '
1"
#481000000
0"
#481500000
0!
b0 '
1"
#482000000
0"
#482500000
b1 '
1"
#483000000
0"
#483500000
b10 '
1"
#484000000
0"
#484500000
b11 '
1"
#485000000
0"
#485500000
b100 '
1"
#486000000
0"
#486500000
b101 '
1"
#487000000
0"
#487500000
b110 '
1"
#488000000
0"
#488500000
b111 '
1"
#489000000
0"
#489500000
b1000 '
1"
#490000000
0"
#490500000
b1001 '
1"
#491000000
0"
#491500000
b1010 '
1"
#492000000
0"
#492500000
b1011 '
1"
#493000000
0"
#493500000
1!
b0 '
1"
#494000000
0"
#494500000
b1 '
1"
#495000000
0"
#495500000
b10 '
1"
#496000000
0"
#496500000
b11 '
1"
#497000000
0"
#497500000
b100 '
1"
#498000000
0"
#498500000
b101 '
1"
#499000000
0"
#499500000
b110 '
1"
#500000000
0"
#500500000
b111 '
1"
#501000000
0"
#501500000
b1000 '
1"
#502000000
0"
#502500000
b1001 '
1"
#503000000
0"
#503500000
b1010 '
1"
#504000000
0"
#504500000
b1011 '
1"
#505000000
0"
#505500000
0!
b0 '
1"
#506000000
0"
#506500000
b1 '
1"
#507000000
0"
#507500000
b10 '
1"
#508000000
0"
#508500000
b11 '
1"
#509000000
0"
#509500000
b100 '
1"
#510000000
0"
#510500000
b101 '
1"
#511000000
0"
#511500000
b110 '
1"
#512000000
0"
#512500000
b111 '
1"
#513000000
0"
#513500000
b1000 '
1"
#514000000
0"
#514500000
b1001 '
1"
#515000000
0"
#515500000
b1010 '
1"
#516000000
0"
#516500000
b1011 '
1"
#517000000
0"
#517500000
1!
b0 '
1"
#518000000
0"
#518500000
b1 '
1"
#519000000
0"
#519500000
b10 '
1"
#520000000
0"
#520500000
b11 '
1"
#521000000
0"
#521500000
b100 '
1"
#522000000
0"
#522500000
b101 '
1"
#523000000
0"
#523500000
b110 '
1"
#524000000
0"
#524500000
b111 '
1"
#525000000
0"
#525500000
b1000 '
1"
#526000000
0"
#526500000
b1001 '
1"
#527000000
0"
#527500000
b1010 '
1"
#528000000
0"
#528500000
b1011 '
1"
#529000000
0"
#529500000
0!
b0 '
1"
#530000000
0"
#530500000
b1 '
1"
#531000000
0"
#531500000
b10 '
1"
#532000000
0"
#532500000
b11 '
1"
#533000000
0"
#533500000
b100 '
1"
#534000000
0"
#534500000
b101 '
1"
#535000000
0"
#535500000
b110 '
1"
#536000000
0"
#536500000
b111 '
1"
#537000000
0"
#537500000
b1000 '
1"
#538000000
0"
#538500000
b1001 '
1"
#539000000
0"
#539500000
b1010 '
1"
#540000000
0"
#540500000
b1011 '
1"
#541000000
0"
#541500000
1!
b0 '
1"
#542000000
0"
#542500000
b1 '
1"
#543000000
0"
#543500000
b10 '
1"
#544000000
0"
#544500000
b11 '
1"
#545000000
0"
#545500000
b100 '
1"
#546000000
0"
#546500000
b101 '
1"
#547000000
0"
#547500000
b110 '
1"
#548000000
0"
#548500000
b111 '
1"
#549000000
0"
#549500000
b1000 '
1"
#550000000
0"
#550500000
b1001 '
1"
#551000000
0"
#551500000
b1010 '
1"
#552000000
0"
#552500000
b1011 '
1"
#553000000
0"
#553500000
0!
b0 '
1"
#554000000
0"
#554500000
b1 '
1"
#555000000
0"
#555500000
b10 '
1"
#556000000
0"
#556500000
b11 '
1"
#557000000
0"
#557500000
b100 '
1"
#558000000
0"
#558500000
b101 '
1"
#559000000
0"
#559500000
b110 '
1"
#560000000
0"
#560500000
b111 '
1"
#561000000
0"
#561500000
b1000 '
1"
#562000000
0"
#562500000
b1001 '
1"
#563000000
0"
#563500000
b1010 '
1"
#564000000
0"
#564500000
b1011 '
1"
#565000000
0"
#565500000
1!
b0 '
1"
#566000000
0"
#566500000
b1 '
1"
#567000000
0"
#567500000
b10 '
1"
#568000000
0"
#568500000
b11 '
1"
#569000000
0"
#569500000
b100 '
1"
#570000000
0"
#570500000
b101 '
1"
#571000000
0"
#571500000
b110 '
1"
#572000000
0"
#572500000
b111 '
1"
#573000000
0"
#573500000
b1000 '
1"
#574000000
0"
#574500000
b1001 '
1"
#575000000
0"
#575500000
b1010 '
1"
#576000000
0"
#576500000
b1011 '
1"
#577000000
0"
#577500000
0!
b0 '
1"
#578000000
0"
#578500000
b1 '
1"
#579000000
0"
#579500000
b10 '
1"
#580000000
0"
#580500000
b11 '
1"
#581000000
0"
#581500000
b100 '
1"
#582000000
0"
#582500000
b101 '
1"
#583000000
0"
#583500000
b110 '
1"
#584000000
0"
#584500000
b111 '
1"
#585000000
0"
#585500000
b1000 '
1"
#586000000
0"
#586500000
b1001 '
1"
#587000000
0"
#587500000
b1010 '
1"
#588000000
0"
#588500000
b1011 '
1"
#589000000
0"
#589500000
1!
b0 '
1"
#590000000
0"
#590500000
b1 '
1"
#591000000
0"
#591500000
b10 '
1"
#592000000
0"
#592500000
b11 '
1"
#593000000
0"
#593500000
b100 '
1"
#594000000
0"
#594500000
b101 '
1"
#595000000
0"
#595500000
b110 '
1"
#596000000
0"
#596500000
b111 '
1"
#597000000
0"
#597500000
b1000 '
1"
#598000000
0"
#598500000
b1001 '
1"
#599000000
0"
#599500000
b1010 '
1"
#600000000
0"
#600500000
b1011 '
1"
#601000000
0"
#601500000
0!
b0 '
1"
#602000000
0"
#602500000
b1 '
1"
#603000000
0"
#603500000
b10 '
1"
#604000000
0"
#604500000
b11 '
1"
#605000000
0"
#605500000
b100 '
1"
#606000000
0"
#606500000
b101 '
1"
#607000000
0"
#607500000
b110 '
1"
#608000000
0"
#608500000
b111 '
1"
#609000000
0"
#609500000
b1000 '
1"
#610000000
0"
#610500000
b1001 '
1"
#611000000
0"
#611500000
b1010 '
1"
#612000000
0"
#612500000
b1011 '
1"
#613000000
0"
#613500000
1!
b0 '
1"
#614000000
0"
#614500000
b1 '
1"
#615000000
0"
#615500000
b10 '
1"
#616000000
0"
#616500000
b11 '
1"
#617000000
0"
#617500000
b100 '
1"
#618000000
0"
#618500000
b101 '
1"
#619000000
0"
#619500000
b110 '
1"
#620000000
0"
#620500000
b111 '
1"
#621000000
0"
#621500000
b1000 '
1"
#622000000
0"
#622500000
b1001 '
1"
#623000000
0"
#623500000
b1010 '
1"
#624000000
0"
#624500000
b1011 '
1"
#625000000
0"
#625500000
0!
b0 '
1"
#626000000
0"
#626500000
b1 '
1"
#627000000
0"
#627500000
b10 '
1"
